iw_config_parser/__init__.py
iw_config_parser/iw_config_parser.py
iw_config_parser-0.0.2.dist-info/LICENSE
iw_config_parser-0.0.2.dist-info/METADATA
iw_config_parser-0.0.2.dist-info/WHEEL
iw_config_parser-0.0.2.dist-info/top_level.txt
iw_config_parser-0.0.2.dist-info/RECORD
