Metadata-Version: 2.1
Name: iw-config-parser
Version: 0.0.2
Summary: Simplify the management of configuration files in your Python projects
Home-page: https://github.com/
Author: iw-infra team
Author-email: has.cha.89@gmail.com
License: MIT
Platform: UNKNOWN
Classifier: License :: OSI Approved :: MIT License
Classifier: Programming Language :: Python :: 3.10
Classifier: Operating System :: OS Independent
Requires-Python: >=3.9
Requires-Dist: pydantic
Provides-Extra: dev
Requires-Dist: pytest >=7.0 ; extra == 'dev'
Requires-Dist: twine >=4.0.2 ; extra == 'dev'
